setup.py
DTNF31/__init__.py
DTNF31/test.py
DTNF31.egg-info/PKG-INFO
DTNF31.egg-info/SOURCES.txt
DTNF31.egg-info/dependency_links.txt
DTNF31.egg-info/top_level.txt